CHANGES.rst
CONTRIBUTORS.rst
MANIFEST.in
Makefile
README.rst
bootstrap.py
pyproject.toml
requirements.txt
setup.cfg
setup.py
docs/LICENSE.GPL
docs/LICENSE.rst
docs/index.rst
src/imio/__init__.py
src/imio.schedule.egg-info/PKG-INFO
src/imio.schedule.egg-info/SOURCES.txt
src/imio.schedule.egg-info/dependency_links.txt
src/imio.schedule.egg-info/entry_points.txt
src/imio.schedule.egg-info/namespace_packages.txt
src/imio.schedule.egg-info/not-zip-safe
src/imio.schedule.egg-info/requires.txt
src/imio.schedule.egg-info/top_level.txt
src/imio/schedule/__init__.py
src/imio/schedule/config.py
src/imio/schedule/configure.zcml
src/imio/schedule/converter.py
src/imio/schedule/deserializer.py
src/imio/schedule/indexes.py
src/imio/schedule/indexes.zcml
src/imio/schedule/interfaces.py
src/imio/schedule/setuphandlers.py
src/imio/schedule/testing.py
src/imio/schedule/testing.zcml
src/imio/schedule/utils.py
src/imio/schedule/vocabularies.py
src/imio/schedule/vocabularies.zcml
src/imio/schedule/browser/__init__.py
src/imio/schedule/browser/close_task.py
src/imio/schedule/browser/configure.zcml
src/imio/schedule/browser/task_completion.py
src/imio/schedule/browser/task_owner.py
src/imio/schedule/browser/overrides/.gitkeep
src/imio/schedule/browser/static/.gitkeep
src/imio/schedule/browser/static/overlay.js
src/imio/schedule/browser/static/schedule.css
src/imio/schedule/browser/templates/close_task.pt
src/imio/schedule/browser/templates/task_change_owner.pt
src/imio/schedule/browser/templates/task_completion.pt
src/imio/schedule/browser/templates/taskmacros.pt
src/imio/schedule/collectionwidget/__init__.py
src/imio/schedule/collectionwidget/configure.zcml
src/imio/schedule/collectionwidget/views.py
src/imio/schedule/collectionwidget/vocabulary.py
src/imio/schedule/collectionwidget/templates/term.pt
src/imio/schedule/content/__init__.py
src/imio/schedule/content/condition.py
src/imio/schedule/content/conditions.zcml
src/imio/schedule/content/configure.zcml
src/imio/schedule/content/delay.py
src/imio/schedule/content/delay.zcml
src/imio/schedule/content/logic.py
src/imio/schedule/content/logic.zcml
src/imio/schedule/content/object_factories.py
src/imio/schedule/content/object_factories.zcml
src/imio/schedule/content/schedule_config.py
src/imio/schedule/content/subform_context_choice.py
src/imio/schedule/content/task.py
