Metadata-Version: 2.1
Name: imio.schedule
Version: 3.0.0
Summary: Schedule for imio products
Home-page: https://pypi.python.org/pypi/imio.schedule
Author: Simon Delcourt
Author-email: simon.delcourt@imio.be
License: GPL version 2
Keywords: Python Plone
Classifier: Environment :: Web Environment
Classifier: Framework :: Plone
Classifier: Framework :: Plone :: 4.3
Classifier: Programming Language :: Python
Classifier: Programming Language :: Python :: 2.7
Classifier: Operating System :: OS Independent
Classifier: License :: OSI Approved :: GNU General Public License v2 (GPLv2)
Provides-Extra: test
